certbot_regfish_hooks/__init__.py
certbot_regfish_hooks/__version__.py
certbot_regfish_hooks/cli.py
certbot_regfish_hooks/hooks.py
certbot_regfish_hooks/api/__init__.py
certbot_regfish_hooks/api/client.py
certbot_regfish_hooks/api/models.py
certbot_regfish_hooks-2.0.0b3.dist-info/LICENSE
certbot_regfish_hooks-2.0.0b3.dist-info/METADATA
certbot_regfish_hooks-2.0.0b3.dist-info/WHEEL
certbot_regfish_hooks-2.0.0b3.dist-info/entry_points.txt
certbot_regfish_hooks-2.0.0b3.dist-info/top_level.txt
certbot_regfish_hooks-2.0.0b3.dist-info/RECORD
