Metadata-Version: 2.1
Name: certbot-regfish-hooks
Version: 2.0.0b3
Summary: regfish pre and post validation hooks for certbot
Author-email: Maximilian Kaulmann <exioreed@ownlink.eu>
License: Copyright 2024 Maximilian Kaulmann
Project-URL: GitHub, https://github.com/exioReed/certbot-regfish-hooks
Classifier: Development Status :: 4 - Beta
Classifier: Environment :: Plugins
Classifier: Intended Audience :: Developers
Classifier: Intended Audience :: System Administrators
Classifier: License :: OSI Approved :: BSD License
Classifier: Programming Language :: Python :: 3
Classifier: Topic :: Internet :: Name Service (DNS)
Classifier: Topic :: Internet :: WWW/HTTP
Classifier: Topic :: Security
Requires-Python: >=3.9
License-File: LICENSE
Requires-Dist: pydantic<2.11.0,>=2.9.2
Requires-Dist: requests~=2.32.3
Provides-Extra: dev
Requires-Dist: pre-commit~=4.0; extra == "dev"
